kbbi_scraper/__init__.py
kbbi_scraper/constants.py
kbbi_scraper/utils.py
kbbi_scraper/word.py
kbbi_scraper-0.0.5.dist-info/LICENSE
kbbi_scraper-0.0.5.dist-info/METADATA
kbbi_scraper-0.0.5.dist-info/WHEEL
kbbi_scraper-0.0.5.dist-info/top_level.txt
kbbi_scraper-0.0.5.dist-info/RECORD
