Metadata-Version: 2.1
Name: kbbi-scraper
Version: 0.0.5
Summary: https://kbbi.web.id/ scraper
Author: Hariz Sufyan Munawar
Author-email: munawarhariz@gmail.com
License: Apache License
License-File: LICENSE
Requires-Dist: selenium
Requires-Dist: beautifulsoup4
Requires-Dist: chromedriver-autoinstaller
